[{"id":"563e15c2db30bf28","type":"ctrlx-datalayer-request","z":"201ba7c7148a7cc2","device":"7b877229.678964","method":"CREATE","path":"motion/kin/Robot/cmd/abort","payloadFormat":"value_type","name":"\"Robot\" abort","x":670,"y":120,"wires":[[]]},{"id":"ac7a8b1446a1e812","type":"ui_button","z":"201ba7c7148a7cc2","name":"","group":"85755e14b124f041","order":3,"width":"3","height":"1","passthru":false,"label":"Abort \"Robot\"","tooltip":"","color":"","bgcolor":"","className":"","icon":"","payload":"","payloadType":"str","topic":"topic","topicType":"msg","x":220,"y":160,"wires":[["558c61d4c8d9c1ac"]]},{"id":"4175c5684253f0db","type":"inject","z":"201ba7c7148a7cc2","name":"Manual Trigger","props":[{"p":"payload"},{"p":"topic","vt":"str"}],"repeat":"","crontab":"","once":false,"onceDelay":0.1,"topic":"","payload":"","payloadType":"date","x":200,"y":120,"wires":[["558c61d4c8d9c1ac"]]},{"id":"64da5a64be4f7a30","type":"comment","z":"201ba7c7148a7cc2","name":"Example: Abort command kinematic \"Robot\"","info":"","x":250,"y":80,"wires":[]},{"id":"558c61d4c8d9c1ac","type":"function","z":"201ba7c7148a7cc2","name":"make abort command","func":"var newMsg = {};\nnewMsg.payload = {\n    \"type\": \"object\",\n    \"value\": {}\n};\nreturn newMsg;","outputs":1,"noerr":0,"initialize":"","finalize":"","libs":[],"x":440,"y":120,"wires":[["563e15c2db30bf28"]]},{"id":"7b877229.678964","type":"ctrlx-config","name":"localhost","hostname":"localhost","debug":false},{"id":"85755e14b124f041","type":"ui_group","name":"Kinematic Handling","tab":"9cba2148.8c9148","order":3,"disp":true,"width":"6","collapse":false,"className":""},{"id":"9cba2148.8c9148","type":"ui_tab","name":"Examples","icon":"dashboard","order":7,"disabled":false,"hidden":false}]