[{"id":"9df4d3fd.3d9218","type":"function","z":"4ff80d56.dd60fc","name":"make file execute command","func":"var newMsg = {};\nnewMsg.payload = {\n    \"type\":\"object\",\n    \"value\":{\n        \"name\":\"activeConfiguration/test.py\" //File test.py expected at root of the active configuration\n        }\n    }\nreturn newMsg;","outputs":1,"noerr":0,"initialize":"","finalize":"","libs":[],"x":440,"y":2320,"wires":[["374d357d.cb126a"]]},{"id":"d4d2cc18.9e9c1","type":"inject","z":"4ff80d56.dd60fc","name":"Manual Trigger","props":[{"p":"payload"},{"p":"topic","vt":"str"}],"repeat":"","crontab":"","once":false,"onceDelay":0.1,"topic":"","payload":"","payloadType":"date","x":180,"y":2360,"wires":[["9df4d3fd.3d9218"]]},{"id":"374d357d.cb126a","type":"ctrlx-datalayer-request","z":"4ff80d56.dd60fc","device":"7b877229.678964","method":"CREATE","path":"script/instances/MyInstance/cmd/file","payloadFormat":"value_type","name":"Execute File \"test.py\"","x":700,"y":2320,"wires":[[]]},{"id":"c0963556.392e7","type":"comment","z":"4ff80d56.dd60fc","name":"Example: Execute a python file \"test.py\" in an instance \"MyInstance\"","info":"","x":320,"y":2280,"wires":[]},{"id":"9df3a70d.0d6f68","type":"ui_button","z":"4ff80d56.dd60fc","name":"","group":"f675e9d2.c9935","order":1,"width":"3","height":"1","passthru":false,"label":"Execute file","tooltip":"","color":"","bgcolor":"","icon":"","payload":"","payloadType":"str","topic":"topic","topicType":"msg","x":190,"y":2320,"wires":[["9df4d3fd.3d9218"]]},{"id":"7b877229.678964","type":"ctrlx-config","name":"localhost","hostname":"localhost","debug":false},{"id":"f675e9d2.c9935","type":"ui_group","name":"Interpreter handling","tab":"9cba2148.8c9148","order":4,"disp":true,"width":"4","collapse":false},{"id":"9cba2148.8c9148","type":"ui_tab","name":"Examples","icon":"dashboard","order":7,"disabled":false,"hidden":false}]